objxmlmodify/__init__.py
objxmlmodify/_test.py
objxmlmodify-1.1.0.dist-info/METADATA
objxmlmodify-1.1.0.dist-info/WHEEL
objxmlmodify-1.1.0.dist-info/top_level.txt
objxmlmodify-1.1.0.dist-info/RECORD
