Metadata-Version: 2.1
Name: objxmlmodify
Version: 1.1.0
Summary: Allows you to modify objects via XML
Home-page: UNKNOWN
Author: Alan Bagel
Author-email: jiuprogrammer@gmail.com
License: UNKNOWN
Platform: UNKNOWN
